pystructtype/__init__.py
pystructtype/bitstype.py
pystructtype/py.typed
pystructtype/structdataclass.py
pystructtype/structtypes.py
pystructtype/utils.py
pystructtype-0.3.0.dist-info/METADATA
pystructtype-0.3.0.dist-info/WHEEL
pystructtype-0.3.0.dist-info/licenses/LICENSE.txt
pystructtype-0.3.0.dist-info/RECORD
