Metadata-Version: 2.4
Name: pystructtype
Version: 0.3.0
Summary: Leverage Python Types to Define C-Struct Interfaces
Project-URL: Homepage, https://github.com/fchorney/pystructtype
Project-URL: Documentation, https://pystructtype.readthedocs.io/en/latest/
Project-URL: Repository, https://github.com/fchorney/pystructtype
Project-URL: Issues, https://github.com/fchorney/pystructtype/issues
Author-email: fchorney <github@djsbx.com>
License-Expression: MIT
License-File: LICENSE.txt
Keywords: cstruct,struct,type
Classifier: Development Status :: 3 - Alpha
Classifier: Intended Audience :: Developers
Classifier: License :: OSI Approved :: MIT License
Classifier: Natural Language :: English
Classifier: Operating System :: OS Independent
Classifier: Programming Language :: Python :: 3.13
Classifier: Topic :: Utilities
Requires-Python: >=3.13
